yugo_booking_lib/__init__.py
yugo_booking_lib/pricing.py
yugo_booking_lib-0.0.2.dist-info/METADATA
yugo_booking_lib-0.0.2.dist-info/WHEEL
yugo_booking_lib-0.0.2.dist-info/RECORD
