Metadata-Version: 2.4
Name: yugo-booking-lib
Version: 0.0.2
Summary: Booking price helper library for Yugo Accommodation.
Project-URL: Homepage, https://github.com/<your_github>/yugo-booking-lib
Project-URL: Bug Tracker, https://github.com/<your_github>/yugo-booking-lib/issues
Author-email: Vishal Verma <your-email@example.com>
Classifier: License :: OSI Approved :: MIT License
Classifier: Operating System :: OS Independent
Classifier: Programming Language :: Python :: 3
Requires-Python: >=3.9
